WeilaiYinxingDtShidaiZhongguoYinxingyeFazhanDeXinqidianFix1/README.md
WeilaiYinxingDtShidaiZhongguoYinxingyeFazhanDeXinqidianFix1/__init__.py
WeilaiYinxingDtShidaiZhongguoYinxingyeFazhanDeXinqidianFix1/__main__.py
WeilaiYinxingDtShidaiZhongguoYinxingyeFazhanDeXinqidianFix1/file.pdf
WeilaiYinxingDtShidaiZhongguoYinxingyeFazhanDeXinqidianFix1/index.html
weilai_yinxing_dt_shidai_zhongguo_yinxingye_fazhan_de_xinqidian_fix1-2025.3.25.1.dist-info/METADATA
weilai_yinxing_dt_shidai_zhongguo_yinxingye_fazhan_de_xinqidian_fix1-2025.3.25.1.dist-info/WHEEL
weilai_yinxing_dt_shidai_zhongguo_yinxingye_fazhan_de_xinqidian_fix1-2025.3.25.1.dist-info/entry_points.txt
weilai_yinxing_dt_shidai_zhongguo_yinxingye_fazhan_de_xinqidian_fix1-2025.3.25.1.dist-info/top_level.txt
weilai_yinxing_dt_shidai_zhongguo_yinxingye_fazhan_de_xinqidian_fix1-2025.3.25.1.dist-info/RECORD
